dynapydantic/__init__.py
dynapydantic/exceptions.py
dynapydantic/py.typed
dynapydantic/subclass_tracking_model.py
dynapydantic/tracking_group.py
dynapydantic-0.1.1.dist-info/METADATA
dynapydantic-0.1.1.dist-info/WHEEL
dynapydantic-0.1.1.dist-info/licenses/LICENSE
dynapydantic-0.1.1.dist-info/RECORD
