Metadata-Version: 2.4
Name: dynapydantic
Version: 0.1.1
Summary: Dyanmic pydantic models
Author-email: Philip Salvaggio <salvaggio.philip@gmail.com>
License-File: LICENSE
Requires-Python: >=3.10
Requires-Dist: pydantic>=2.0
